lightrag/api/__init__.py
lightrag/api/_async_client.py
lightrag/api/_exceptions.py
lightrag/api/_schemas.py
lightrag/api/_sync_client.py
lightrag_api-0.1.4.dist-info/METADATA
lightrag_api-0.1.4.dist-info/WHEEL
lightrag_api-0.1.4.dist-info/top_level.txt
lightrag_api-0.1.4.dist-info/RECORD
