Metadata-Version: 2.4
Name: lightrag-api
Version: 0.1.4
Summary: Simple LightRAG API client
Author-email: ivkond <ivkond@gmail.com>
License-Expression: MIT
Project-URL: Repository, https://github.com/ivkond/lightrag-api.git
Keywords: rag,lightrag
Requires-Python: >=3.10
Requires-Dist: httpx>=0.28.1
Requires-Dist: pydantic>=2.12.5
